CHANGES.rst
MANIFEST.in
README.rst
setup.cfg
setup.py
pyramid_contextauth/__init__.py
pyramid_contextauth.egg-info/PKG-INFO
pyramid_contextauth.egg-info/SOURCES.txt
pyramid_contextauth.egg-info/dependency_links.txt
pyramid_contextauth.egg-info/requires.txt
pyramid_contextauth.egg-info/top_level.txt