Metadata-Version: 1.0
Name: pyramid-contextauth
Version: 0.7
Summary: 
Home-page: https://github.com/hadrien/pyramid_contextauth
Author: Hadrien David
Author-email: hadrien@ectobal.com
License: BSD-derived (http://www.repoze.org/LICENSE.txt)
Platform: UNKNOWN
